{
  "id": "LCW-5393752",
  "retailer": "lcwaikiki",
  "deeplink": "https://www.lcw.com/kadin-yeni-bej-dolgu-topuklu-arkasi-acik-ayakkabi-bej-o-5393752",
  "photos": {
    "front": "/products/lcwaikiki/lcw-5393752/front.jpg"
  },
  "name": "Bej Kadın YENİ BEJ Dolgu Topuklu Arkası Açık Ayakkabı",
  "priceText": "2263.06",
  "price": 2263.06,
  "breadcrumb": "Ana SayfaKadınKadın AyakkabıKadın Topuklu AyakkabıKadın YENİ BEJ Dolgu Topuklu Arkası Açık Ayakkabı",
  "gender": "kadin",
  "category": "ayakkabi",
  "updatedAt": "2026-05-16T19:54:42.300Z"
}