{
  "id": "LCW-4775995",
  "retailer": "lcwaikiki",
  "deeplink": "https://www.lcw.com/kadin-zumrut-siyah-bantli-kadeh-okce-sandalet-mor-o-4775995",
  "photos": {
    "front": "/products/lcwaikiki/lcw-4775995/front.jpg"
  },
  "name": "Mor Kadın ZÜMRÜT-SİYAH Bantlı Kadeh Ökçe Sandalet",
  "priceText": "2705.17",
  "price": 2705.17,
  "breadcrumb": "Ana SayfaKadınKadın AyakkabıKadın Topuklu AyakkabıKadın ZÜMRÜT-SİYAH Bantlı Kadeh Ökçe Sandalet",
  "gender": "kadin",
  "category": "ayakkabi",
  "updatedAt": "2026-05-16T19:51:32.949Z"
}