{
  "id": "LCW-5205905",
  "retailer": "lcwaikiki",
  "deeplink": "https://www.lcw.com/gomlek-yaka-kadin-jean-ceket-indigo-o-5205905",
  "photos": {
    "front": "/products/lcwaikiki/lcw-5205905/front.jpg",
    "back": "/products/lcwaikiki/lcw-5205905/back.jpg",
    "garmentFront": "/products/lcwaikiki/lcw-5205905/garmentFront.jpg"
  },
  "name": "İndigo Gömlek Yaka Kadın Jean Ceket",
  "priceText": "899.99",
  "price": 899.99,
  "breadcrumb": "Ana SayfaKadınKadın GiyimKadın Dış GiyimKadın CeketKadın Jean CeketGömlek Yaka Kadın Jean Ceket",
  "gender": "kadin",
  "category": "ust-giyim",
  "updatedAt": "2026-05-16T22:59:38.987Z"
}