{
  "id": "LCW-4168431",
  "retailer": "lcwaikiki",
  "deeplink": "https://www.lcw.com/atomix-kadin-sneaker-ayakkabi-siyah-beyaz-siyah-o-4168431",
  "photos": {
    "front": "/products/lcwaikiki/lcw-4168431/front.jpg"
  },
  "name": "ATOMIX Kadın Sneaker Ayakkabı Siyah / Beyaz",
  "priceText": "1509.90",
  "price": 1509.9,
  "breadcrumb": "Ana SayfaKadınKadın AyakkabıKadın Spor AyakkabıKadın SneakerATOMIX Kadın Sneaker Ayakkabı Siyah / Beyaz",
  "gender": "kadin",
  "category": "ayakkabi",
  "updatedAt": "2026-05-16T13:55:50.119Z"
}