{
  "id": "LCW-5390008",
  "retailer": "lcwaikiki",
  "deeplink": "https://www.lcw.com/kadin-kahverengi-taba-tokali-feta-dolgulu-ayakkabi-kahverengi-o-5390008",
  "photos": {
    "front": "/products/lcwaikiki/lcw-5390008/front.jpg"
  },
  "name": "Kahverengi Kadın KAHVERENGİ-TABA Tokalı Feta Dolgulu Ayakkabı",
  "priceText": "2484.12",
  "price": 2484.12,
  "breadcrumb": "Ana SayfaKadınKadın AyakkabıKadın Topuklu AyakkabıKadın KAHVERENGİ-TABA Tokalı Feta Dolgulu Ayakkabı",
  "gender": "kadin",
  "category": "ayakkabi",
  "updatedAt": "2026-05-16T19:40:21.085Z"
}